bllog/__init__.py
bllog/fomat.py
bllog/log_classes.py
bllog/logger.py
bllog/stream.py
bllog-1.0.0.dist-info/METADATA
bllog-1.0.0.dist-info/WHEEL
bllog-1.0.0.dist-info/top_level.txt
bllog-1.0.0.dist-info/RECORD
