Metadata-Version: 2.1
Name: bllog
Version: 1.0.0
Summary: Simple and easy-to-use logger
Home-page: https://github.com/barrow099/bllog
Author: Barrow099 (Mate Magyar)
Author-email: mate@barrow099.hu
License: MIT
Platform: UNKNOWN
Classifier: License :: OSI Approved :: MIT License
Classifier: Programming Language :: Python :: 3
Classifier: Programming Language :: Python :: 3.8
Requires-Dist: colorama
Requires-Dist: termcolor
